auquan_toolbox_beta-1.1.4.dist-info/METADATA
auquan_toolbox_beta-1.1.4.dist-info/RECORD
auquan_toolbox_beta-1.1.4.dist-info/WHEEL
auquan_toolbox_beta-1.1.4.dist-info/top_level.txt
backtester/__init__.py
backtester/configurator.py
backtester/constants.py
backtester/financial_fn.py
backtester/instruments_lookback_data.py
backtester/instruments_manager.py
backtester/logger.py
backtester/lookback_data.py
backtester/model_data.py
backtester/model_learning_and_trading_system.py
backtester/model_learning_system.py
backtester/model_learning_system_parameters.py
backtester/plotter.py
backtester/process_result.py
backtester/state_writer.py
backtester/trading_system.py
backtester/trading_system_parameters.py
backtester/version.py
backtester/dataSource/__init__.py
backtester/dataSource/auquan_data_source.py
backtester/dataSource/csv_data_source.py
backtester/dataSource/data_source.py
backtester/dataSource/data_source_classes.py
backtester/dataSource/data_source_utils.py
backtester/dataSource/features_data_source.py
backtester/dataSource/future_role_data_source.py
backtester/dataSource/google_data_source.py
backtester/dataSource/logfile_data_source.py
backtester/dataSource/nse_data_source.py
backtester/dataSource/quandl_data_source.py
backtester/dataSource/quant_quest_data_source.py
backtester/dataSource/yahoo_data_source.py
backtester/executionSystem/QQ_execution_system.py
backtester/executionSystem/__init__.py
backtester/executionSystem/base_execution_system.py
backtester/executionSystem/basis_execution_system.py
backtester/executionSystem/pair_execution_system.py
backtester/executionSystem/simple_execution_system.py
backtester/executionSystem/simple_execution_system_fairvalue.py
backtester/featureSelection/__init__.py
backtester/featureSelection/correlation.py
backtester/featureSelection/feature_selection.py
backtester/featureSelection/feature_selection_config.py
backtester/featureSelection/generic_univariate_select.py
backtester/featureSelection/rfecv_selection.py
backtester/featureSelection/supervised_learning_estimator.py
backtester/features/__init__.py
backtester/features/argmax_feature.py
